betterproto/__init__.py
betterproto/_types.py
betterproto/_version.py
betterproto/casing.py
betterproto/compile/__init__.py
betterproto/compile/importing.py
betterproto/compile/naming.py
betterproto/grpc/__init__.py
betterproto/grpc/grpclib_client.py
betterproto/grpc/grpclib_server.py
betterproto/grpc/util/__init__.py
betterproto/grpc/util/async_channel.py
betterproto/lib/__init__.py
betterproto/lib/google/__init__.py
betterproto/lib/google/protobuf/__init__.py
betterproto/lib/google/protobuf/compiler/__init__.py
betterproto/plugin/__init__.py
betterproto/plugin/__main__.py
betterproto/plugin/compiler.py
betterproto/plugin/main.py
betterproto/plugin/models.py
betterproto/plugin/parser.py
betterproto/plugin/plugin.bat
betterproto/py.typed
betterproto/templates/template.py.j2
avast.betterproto-0.3.1.dist-info/entry_points.txt
avast.betterproto-0.3.1.dist-info/WHEEL
avast.betterproto-0.3.1.dist-info/METADATA
avast.betterproto-0.3.1.dist-info/RECORD
