Metadata-Version: 2.1
Name: avast.betterproto
Version: 0.3.1
Summary: A better Protobuf / gRPC generator & library
Home-page: https://github.com/danielgtaylor/python-betterproto
License: MIT
Keywords: protobuf,gRPC
Author: Daniel G. Taylor
Author-email: danielgtaylor@gmail.com
Requires-Python: >=3.6.2,<4.0
Classifier: License :: OSI Approved :: MIT License
Classifier: Programming Language :: Python :: 3
Classifier: Programming Language :: Python :: 3.10
Classifier: Programming Language :: Python :: 3.7
Classifier: Programming Language :: Python :: 3.8
Classifier: Programming Language :: Python :: 3.9
Provides-Extra: compiler
Requires-Dist: black (>=19.3b0); extra == "compiler"
Requires-Dist: dataclasses (>=0.7,<0.8); python_version >= "3.6" and python_version < "3.7"
Requires-Dist: grpclib (>=0.4.1,<0.5.0)
Requires-Dist: jinja2 (>=2.11.2,<3.0.0); extra == "compiler"
Requires-Dist: python-dateutil (>=2.8,<3.0)
Project-URL: Repository, https://github.com/danielgtaylor/python-betterproto
